flipwizard/__init__.py
flipwizard/authorization.py
flipwizard/crash.py
flipwizard/currency.py
flipwizard/jackpot.py
flipwizard/mines.py
flipwizard/towers.py
flipwizard-1.0.0.dist-info/LICENSE
flipwizard-1.0.0.dist-info/METADATA
flipwizard-1.0.0.dist-info/WHEEL
flipwizard-1.0.0.dist-info/top_level.txt
flipwizard-1.0.0.dist-info/RECORD
