Metadata-Version: 2.1
Name: flipwizard
Version: 1.0.0
Summary: An api wrapper for https://bloxflip.com
Home-page: UNKNOWN
Author: zappy
Author-email: UNKNOWN
License: UNKNOWN
Platform: UNKNOWN
